<?xml version="1.0" encoding="utf-8" standalone="yes"?>
<Input playerOneDefault="KeyboardAndMouse" playerTwoDefault="Windows_Gamepad1" playerThreeDefault="Windows_Gamepad2" playerFourDefault="Windows_Gamepad3">
  <InputConfiguration name="KeyboardAndMouse">
    <AxisConfiguration name="Horizontal">
      <description />
      <positive>D</positive>
      <altPositive>None</altPositive>
      <negative>A</negative>
      <altNegative>None</altNegative>
      <deadZone>0</deadZone>
      <gravity>3</gravity>
      <sensitivity>3</sensitivity>
      <snap>true</snap>
      <invert>false</invert>
      <type>DigitalAxis</type>
      <axis>0</axis>
      <joystick>0</joystick>
    </AxisConfiguration>
    <AxisConfiguration name="Vertical">
      <description />
      <positive>W</positive>
      <altPositive>None</altPositive>
      <negative>S</negative>
      <altNegative>None</altNegative>
      <deadZone>0</deadZone>
      <gravity>3</gravity>
      <sensitivity>3</sensitivity>
      <snap>true</snap>
      <invert>false</invert>
      <type>DigitalAxis</type>
      <axis>0</axis>
      <joystick>0</joystick>
    </AxisConfiguration>
    <AxisConfiguration name="LookHorizontal">
      <description />
      <positive>None</positive>
      <altPositive>None</altPositive>
      <negative>None</negative>
      <altNegative>None</altNegative>
      <deadZone>0</deadZone>
      <gravity>1</gravity>
      <sensitivity>0.1</sensitivity>
      <snap>false</snap>
      <invert>false</invert>
      <type>MouseAxis</type>
      <axis>0</axis>
      <joystick>0</joystick>
    </AxisConfiguration>
    <AxisConfiguration name="LookVertical">
      <description />
      <positive>None</positive>
      <altPositive>None</altPositive>
      <negative>None</negative>
      <altNegative>None</altNegative>
      <deadZone>0</deadZone>
      <gravity>1</gravity>
      <sensitivity>0.1</sensitivity>
      <snap>false</snap>
      <invert>false</invert>
      <type>MouseAxis</type>
      <axis>1</axis>
      <joystick>0</joystick>
    </AxisConfiguration>
    <AxisConfiguration name="Jump">
      <description />
      <positive>Space</positive>
      <altPositive>None</altPositive>
      <negative>None</negative>
      <altNegative>None</altNegative>
      <deadZone>0</deadZone>
      <gravity>3</gravity>
      <sensitivity>3</sensitivity>
      <snap>true</snap>
      <invert>false</invert>
      <type>DigitalAxis</type>
      <axis>0</axis>
      <joystick>0</joystick>
    </AxisConfiguration>
    <AxisConfiguration name="Fire">
      <description />
      <positive>Mouse0</positive>
      <altPositive>None</altPositive>
      <negative>None</negative>
      <altNegative>None</altNegative>
      <deadZone>0</deadZone>
      <gravity>3</gravity>
      <sensitivity>3</sensitivity>
      <snap>true</snap>
      <invert>false</invert>
      <type>DigitalAxis</type>
      <axis>0</axis>
      <joystick>0</joystick>
    </AxisConfiguration>
    <AxisConfiguration name="Reload">
      <description />
      <positive>R</positive>
      <altPositive>None</altPositive>
      <negative>None</negative>
      <altNegative>None</altNegative>
      <deadZone>0</deadZone>
      <gravity>0</gravity>
      <sensitivity>0</sensitivity>
      <snap>false</snap>
      <invert>false</invert>
      <type>Button</type>
      <axis>0</axis>
      <joystick>0</joystick>
    </AxisConfiguration>
    <AxisConfiguration name="Menu">
      <description />
      <positive>Escape</positive>
      <altPositive>None</altPositive>
      <negative>None</negative>
      <altNegative>None</altNegative>
      <deadZone>0</deadZone>
      <gravity>0</gravity>
      <sensitivity>0</sensitivity>
      <snap>false</snap>
      <invert>false</invert>
      <type>Button</type>
      <axis>0</axis>
      <joystick>0</joystick>
    </AxisConfiguration>
    <AxisConfiguration name="DPADHorizontal">
      <description />
      <positive>L</positive>
      <altPositive>None</altPositive>
      <negative>J</negative>
      <altNegative>None</altNegative>
      <deadZone>0</deadZone>
      <gravity>3</gravity>
      <sensitivity>3</sensitivity>
      <snap>false</snap>
      <invert>false</invert>
      <type>DigitalAxis</type>
      <axis>0</axis>
      <joystick>0</joystick>
    </AxisConfiguration>
    <AxisConfiguration name="DPADVertical">
      <description />
      <positive>I</positive>
      <altPositive>None</altPositive>
      <negative>K</negative>
      <altNegative>None</altNegative>
      <deadZone>0</deadZone>
      <gravity>3</gravity>
      <sensitivity>3</sensitivity>
      <snap>false</snap>
      <invert>false</invert>
      <type>DigitalAxis</type>
      <axis>0</axis>
      <joystick>0</joystick>
    </AxisConfiguration>
    <AxisConfiguration name="RightBumper">
      <description />
      <positive>E</positive>
      <altPositive>None</altPositive>
      <negative>None</negative>
      <altNegative>None</altNegative>
      <deadZone>0</deadZone>
      <gravity>3</gravity>
      <sensitivity>3</sensitivity>
      <snap>false</snap>
      <invert>false</invert>
      <type>Button</type>
      <axis>0</axis>
      <joystick>0</joystick>
    </AxisConfiguration>
    <AxisConfiguration name="LeftBumper">
      <description />
      <positive>Q</positive>
      <altPositive>None</altPositive>
      <negative>None</negative>
      <altNegative>None</altNegative>
      <deadZone>0</deadZone>
      <gravity>3</gravity>
      <sensitivity>3</sensitivity>
      <snap>false</snap>
      <invert>false</invert>
      <type>Button</type>
      <axis>0</axis>
      <joystick>0</joystick>
    </AxisConfiguration>
  </InputConfiguration>
  <InputConfiguration name="Windows_Gamepad1">
    <AxisConfiguration name="Horizontal">
      <description />
      <positive>None</positive>
      <altPositive>None</altPositive>
      <negative>None</negative>
      <altNegative>None</altNegative>
      <deadZone>0.2</deadZone>
      <gravity>0</gravity>
      <sensitivity>1</sensitivity>
      <snap>false</snap>
      <invert>false</invert>
      <type>AnalogAxis</type>
      <axis>0</axis>
      <joystick>0</joystick>
    </AxisConfiguration>
    <AxisConfiguration name="Vertical">
      <description />
      <positive>None</positive>
      <altPositive>None</altPositive>
      <negative>None</negative>
      <altNegative>None</altNegative>
      <deadZone>0.2</deadZone>
      <gravity>0</gravity>
      <sensitivity>1</sensitivity>
      <snap>false</snap>
      <invert>true</invert>
      <type>AnalogAxis</type>
      <axis>1</axis>
      <joystick>0</joystick>
    </AxisConfiguration>
    <AxisConfiguration name="LookHorizontal">
      <description />
      <positive>None</positive>
      <altPositive>None</altPositive>
      <negative>None</negative>
      <altNegative>None</altNegative>
      <deadZone>0.2</deadZone>
      <gravity>0</gravity>
      <sensitivity>1</sensitivity>
      <snap>false</snap>
      <invert>false</invert>
      <type>AnalogAxis</type>
      <axis>3</axis>
      <joystick>0</joystick>
    </AxisConfiguration>
    <AxisConfiguration name="LookVertical">
      <description />
      <positive>None</positive>
      <altPositive>None</altPositive>
      <negative>None</negative>
      <altNegative>None</altNegative>
      <deadZone>0.2</deadZone>
      <gravity>0</gravity>
      <sensitivity>1</sensitivity>
      <snap>false</snap>
      <invert>true</invert>
      <type>AnalogAxis</type>
      <axis>4</axis>
      <joystick>0</joystick>
    </AxisConfiguration>
    <AxisConfiguration name="Jump">
      <description />
      <positive>None</positive>
      <altPositive>None</altPositive>
      <negative>None</negative>
      <altNegative>None</altNegative>
      <deadZone>0</deadZone>
      <gravity>0</gravity>
      <sensitivity>1000</sensitivity>
      <snap>true</snap>
      <invert>false</invert>
      <type>AnalogAxis</type>
      <axis>8</axis>
      <joystick>0</joystick>
    </AxisConfiguration>
    <AxisConfiguration name="Fire">
      <description />
      <positive>None</positive>
      <altPositive>None</altPositive>
      <negative>None</negative>
      <altNegative>None</altNegative>
      <deadZone>0</deadZone>
      <gravity>0</gravity>
      <sensitivity>1000</sensitivity>
      <snap>true</snap>
      <invert>false</invert>
      <type>AnalogAxis</type>
      <axis>9</axis>
      <joystick>0</joystick>
    </AxisConfiguration>
    <AxisConfiguration name="Reload">
      <description />
      <positive>Joystick1Button0</positive>
      <altPositive>None</altPositive>
      <negative>None</negative>
      <altNegative>None</altNegative>
      <deadZone>0</deadZone>
      <gravity>0</gravity>
      <sensitivity>0</sensitivity>
      <snap>false</snap>
      <invert>false</invert>
      <type>Button</type>
      <axis>0</axis>
      <joystick>0</joystick>
    </AxisConfiguration>
    <AxisConfiguration name="Menu">
      <description />
      <positive>Joystick1Button7</positive>
      <altPositive>None</altPositive>
      <negative>None</negative>
      <altNegative>None</altNegative>
      <deadZone>0</deadZone>
      <gravity>0</gravity>
      <sensitivity>0</sensitivity>
      <snap>false</snap>
      <invert>false</invert>
      <type>Button</type>
      <axis>0</axis>
      <joystick>0</joystick>
    </AxisConfiguration>
    <AxisConfiguration name="DPADHorizontal">
      <description />
      <positive>None</positive>
      <altPositive>None</altPositive>
      <negative>None</negative>
      <altNegative>None</altNegative>
      <deadZone>0</deadZone>
      <gravity>0</gravity>
      <sensitivity>1000</sensitivity>
      <snap>true</snap>
      <invert>false</invert>
      <type>AnalogAxis</type>
      <axis>5</axis>
      <joystick>0</joystick>
    </AxisConfiguration>
    <AxisConfiguration name="DPADVertical">
      <description />
      <positive>None</positive>
      <altPositive>None</altPositive>
      <negative>None</negative>
      <altNegative>None</altNegative>
      <deadZone>0</deadZone>
      <gravity>0</gravity>
      <sensitivity>1000</sensitivity>
      <snap>true</snap>
      <invert>false</invert>
      <type>AnalogAxis</type>
      <axis>6</axis>
      <joystick>0</joystick>
    </AxisConfiguration>
    <AxisConfiguration name="RightBumper">
      <description />
      <positive>Joystick1Button5</positive>
      <altPositive>None</altPositive>
      <negative>None</negative>
      <altNegative>None</altNegative>
      <deadZone>0</deadZone>
      <gravity>0</gravity>
      <sensitivity>0</sensitivity>
      <snap>false</snap>
      <invert>false</invert>
      <type>Button</type>
      <axis>0</axis>
      <joystick>0</joystick>
    </AxisConfiguration>
    <AxisConfiguration name="LeftBumper">
      <description />
      <positive>Joystick1Button4</positive>
      <altPositive>None</altPositive>
      <negative>None</negative>
      <altNegative>None</altNegative>
      <deadZone>0</deadZone>
      <gravity>0</gravity>
      <sensitivity>0</sensitivity>
      <snap>false</snap>
      <invert>false</invert>
      <type>Button</type>
      <axis>0</axis>
      <joystick>0</joystick>
    </AxisConfiguration>
  </InputConfiguration>
  <InputConfiguration name="Windows_Gamepad2">
    <AxisConfiguration name="Horizontal">
      <description />
      <positive>None</positive>
      <altPositive>None</altPositive>
      <negative>None</negative>
      <altNegative>None</altNegative>
      <deadZone>0.2</deadZone>
      <gravity>0</gravity>
      <sensitivity>1</sensitivity>
      <snap>false</snap>
      <invert>false</invert>
      <type>AnalogAxis</type>
      <axis>0</axis>
      <joystick>1</joystick>
    </AxisConfiguration>
    <AxisConfiguration name="Vertical">
      <description />
      <positive>None</positive>
      <altPositive>None</altPositive>
      <negative>None</negative>
      <altNegative>None</altNegative>
      <deadZone>0.2</deadZone>
      <gravity>0</gravity>
      <sensitivity>1</sensitivity>
      <snap>false</snap>
      <invert>true</invert>
      <type>AnalogAxis</type>
      <axis>1</axis>
      <joystick>1</joystick>
    </AxisConfiguration>
    <AxisConfiguration name="LookHorizontal">
      <description />
      <positive>None</positive>
      <altPositive>None</altPositive>
      <negative>None</negative>
      <altNegative>None</altNegative>
      <deadZone>0.2</deadZone>
      <gravity>0</gravity>
      <sensitivity>1</sensitivity>
      <snap>false</snap>
      <invert>false</invert>
      <type>AnalogAxis</type>
      <axis>3</axis>
      <joystick>1</joystick>
    </AxisConfiguration>
    <AxisConfiguration name="LookVertical">
      <description />
      <positive>None</positive>
      <altPositive>None</altPositive>
      <negative>None</negative>
      <altNegative>None</altNegative>
      <deadZone>0.2</deadZone>
      <gravity>0</gravity>
      <sensitivity>1</sensitivity>
      <snap>false</snap>
      <invert>true</invert>
      <type>AnalogAxis</type>
      <axis>4</axis>
      <joystick>1</joystick>
    </AxisConfiguration>
    <AxisConfiguration name="Jump">
      <description />
      <positive>None</positive>
      <altPositive>None</altPositive>
      <negative>None</negative>
      <altNegative>None</altNegative>
      <deadZone>0</deadZone>
      <gravity>0</gravity>
      <sensitivity>1000</sensitivity>
      <snap>true</snap>
      <invert>false</invert>
      <type>AnalogAxis</type>
      <axis>8</axis>
      <joystick>1</joystick>
    </AxisConfiguration>
    <AxisConfiguration name="Fire">
      <description />
      <positive>None</positive>
      <altPositive>None</altPositive>
      <negative>None</negative>
      <altNegative>None</altNegative>
      <deadZone>0</deadZone>
      <gravity>0</gravity>
      <sensitivity>1000</sensitivity>
      <snap>true</snap>
      <invert>false</invert>
      <type>AnalogAxis</type>
      <axis>9</axis>
      <joystick>1</joystick>
    </AxisConfiguration>
    <AxisConfiguration name="Reload">
      <description />
      <positive>Joystick2Button0</positive>
      <altPositive>None</altPositive>
      <negative>None</negative>
      <altNegative>None</altNegative>
      <deadZone>0</deadZone>
      <gravity>0</gravity>
      <sensitivity>0</sensitivity>
      <snap>false</snap>
      <invert>false</invert>
      <type>Button</type>
      <axis>0</axis>
      <joystick>1</joystick>
    </AxisConfiguration>
    <AxisConfiguration name="Menu">
      <description />
      <positive>Joystick2Button7</positive>
      <altPositive>None</altPositive>
      <negative>None</negative>
      <altNegative>None</altNegative>
      <deadZone>0</deadZone>
      <gravity>0</gravity>
      <sensitivity>0</sensitivity>
      <snap>false</snap>
      <invert>false</invert>
      <type>Button</type>
      <axis>0</axis>
      <joystick>1</joystick>
    </AxisConfiguration>
    <AxisConfiguration name="DPADHorizontal">
      <description />
      <positive>None</positive>
      <altPositive>None</altPositive>
      <negative>None</negative>
      <altNegative>None</altNegative>
      <deadZone>0</deadZone>
      <gravity>0</gravity>
      <sensitivity>1000</sensitivity>
      <snap>true</snap>
      <invert>false</invert>
      <type>AnalogAxis</type>
      <axis>5</axis>
      <joystick>1</joystick>
    </AxisConfiguration>
    <AxisConfiguration name="DPADVertical">
      <description />
      <positive>None</positive>
      <altPositive>None</altPositive>
      <negative>None</negative>
      <altNegative>None</altNegative>
      <deadZone>0</deadZone>
      <gravity>0</gravity>
      <sensitivity>1000</sensitivity>
      <snap>true</snap>
      <invert>false</invert>
      <type>AnalogAxis</type>
      <axis>6</axis>
      <joystick>1</joystick>
    </AxisConfiguration>
    <AxisConfiguration name="RightBumper">
      <description />
      <positive>Joystick2Button5</positive>
      <altPositive>None</altPositive>
      <negative>None</negative>
      <altNegative>None</altNegative>
      <deadZone>0</deadZone>
      <gravity>0</gravity>
      <sensitivity>0</sensitivity>
      <snap>false</snap>
      <invert>false</invert>
      <type>Button</type>
      <axis>0</axis>
      <joystick>1</joystick>
    </AxisConfiguration>
    <AxisConfiguration name="LeftBumper">
      <description />
      <positive>Joystick2Button4</positive>
      <altPositive>None</altPositive>
      <negative>None</negative>
      <altNegative>None</altNegative>
      <deadZone>0</deadZone>
      <gravity>0</gravity>
      <sensitivity>0</sensitivity>
      <snap>false</snap>
      <invert>false</invert>
      <type>Button</type>
      <axis>0</axis>
      <joystick>1</joystick>
    </AxisConfiguration>
  </InputConfiguration>
  <InputConfiguration name="Windows_Gamepad3">
    <AxisConfiguration name="Horizontal">
      <description />
      <positive>None</positive>
      <altPositive>None</altPositive>
      <negative>None</negative>
      <altNegative>None</altNegative>
      <deadZone>0.2</deadZone>
      <gravity>0</gravity>
      <sensitivity>1</sensitivity>
      <snap>false</snap>
      <invert>false</invert>
      <type>AnalogAxis</type>
      <axis>0</axis>
      <joystick>2</joystick>
    </AxisConfiguration>
    <AxisConfiguration name="Vertical">
      <description />
      <positive>None</positive>
      <altPositive>None</altPositive>
      <negative>None</negative>
      <altNegative>None</altNegative>
      <deadZone>0.2</deadZone>
      <gravity>0</gravity>
      <sensitivity>1</sensitivity>
      <snap>false</snap>
      <invert>true</invert>
      <type>AnalogAxis</type>
      <axis>1</axis>
      <joystick>2</joystick>
    </AxisConfiguration>
    <AxisConfiguration name="LookHorizontal">
      <description />
      <positive>None</positive>
      <altPositive>None</altPositive>
      <negative>None</negative>
      <altNegative>None</altNegative>
      <deadZone>0.2</deadZone>
      <gravity>0</gravity>
      <sensitivity>1</sensitivity>
      <snap>false</snap>
      <invert>false</invert>
      <type>AnalogAxis</type>
      <axis>3</axis>
      <joystick>2</joystick>
    </AxisConfiguration>
    <AxisConfiguration name="LookVertical">
      <description />
      <positive>None</positive>
      <altPositive>None</altPositive>
      <negative>None</negative>
      <altNegative>None</altNegative>
      <deadZone>0.2</deadZone>
      <gravity>0</gravity>
      <sensitivity>1</sensitivity>
      <snap>false</snap>
      <invert>true</invert>
      <type>AnalogAxis</type>
      <axis>4</axis>
      <joystick>2</joystick>
    </AxisConfiguration>
    <AxisConfiguration name="Jump">
      <description />
      <positive>None</positive>
      <altPositive>None</altPositive>
      <negative>None</negative>
      <altNegative>None</altNegative>
      <deadZone>0</deadZone>
      <gravity>0</gravity>
      <sensitivity>1000</sensitivity>
      <snap>true</snap>
      <invert>false</invert>
      <type>AnalogAxis</type>
      <axis>8</axis>
      <joystick>2</joystick>
    </AxisConfiguration>
    <AxisConfiguration name="Fire">
      <description />
      <positive>None</positive>
      <altPositive>None</altPositive>
      <negative>None</negative>
      <altNegative>None</altNegative>
      <deadZone>0</deadZone>
      <gravity>0</gravity>
      <sensitivity>1000</sensitivity>
      <snap>true</snap>
      <invert>false</invert>
      <type>AnalogAxis</type>
      <axis>9</axis>
      <joystick>2</joystick>
    </AxisConfiguration>
    <AxisConfiguration name="Reload">
      <description />
      <positive>Joystick3Button0</positive>
      <altPositive>None</altPositive>
      <negative>None</negative>
      <altNegative>None</altNegative>
      <deadZone>0</deadZone>
      <gravity>0</gravity>
      <sensitivity>0</sensitivity>
      <snap>false</snap>
      <invert>false</invert>
      <type>Button</type>
      <axis>0</axis>
      <joystick>2</joystick>
    </AxisConfiguration>
    <AxisConfiguration name="Menu">
      <description />
      <positive>Joystick3Button7</positive>
      <altPositive>None</altPositive>
      <negative>None</negative>
      <altNegative>None</altNegative>
      <deadZone>0</deadZone>
      <gravity>0</gravity>
      <sensitivity>0</sensitivity>
      <snap>false</snap>
      <invert>false</invert>
      <type>Button</type>
      <axis>0</axis>
      <joystick>2</joystick>
    </AxisConfiguration>
    <AxisConfiguration name="DPADHorizontal">
      <description />
      <positive>None</positive>
      <altPositive>None</altPositive>
      <negative>None</negative>
      <altNegative>None</altNegative>
      <deadZone>0</deadZone>
      <gravity>0</gravity>
      <sensitivity>1000</sensitivity>
      <snap>true</snap>
      <invert>false</invert>
      <type>AnalogAxis</type>
      <axis>5</axis>
      <joystick>2</joystick>
    </AxisConfiguration>
    <AxisConfiguration name="DPADVertical">
      <description />
      <positive>None</positive>
      <altPositive>None</altPositive>
      <negative>None</negative>
      <altNegative>None</altNegative>
      <deadZone>0</deadZone>
      <gravity>0</gravity>
      <sensitivity>1000</sensitivity>
      <snap>true</snap>
      <invert>false</invert>
      <type>AnalogAxis</type>
      <axis>6</axis>
      <joystick>2</joystick>
    </AxisConfiguration>
    <AxisConfiguration name="RightBumper">
      <description />
      <positive>Joystick3Button5</positive>
      <altPositive>None</altPositive>
      <negative>None</negative>
      <altNegative>None</altNegative>
      <deadZone>0</deadZone>
      <gravity>0</gravity>
      <sensitivity>0</sensitivity>
      <snap>false</snap>
      <invert>false</invert>
      <type>Button</type>
      <axis>0</axis>
      <joystick>2</joystick>
    </AxisConfiguration>
    <AxisConfiguration name="LeftBumper">
      <description />
      <positive>Joystick3Button4</positive>
      <altPositive>None</altPositive>
      <negative>None</negative>
      <altNegative>None</altNegative>
      <deadZone>0</deadZone>
      <gravity>0</gravity>
      <sensitivity>0</sensitivity>
      <snap>false</snap>
      <invert>false</invert>
      <type>Button</type>
      <axis>0</axis>
      <joystick>2</joystick>
    </AxisConfiguration>
  </InputConfiguration>
  <InputConfiguration name="Windows_Gamepad4">
    <AxisConfiguration name="Horizontal">
      <description />
      <positive>None</positive>
      <altPositive>None</altPositive>
      <negative>None</negative>
      <altNegative>None</altNegative>
      <deadZone>0.2</deadZone>
      <gravity>0</gravity>
      <sensitivity>1</sensitivity>
      <snap>false</snap>
      <invert>false</invert>
      <type>AnalogAxis</type>
      <axis>0</axis>
      <joystick>3</joystick>
    </AxisConfiguration>
    <AxisConfiguration name="Vertical">
      <description />
      <positive>None</positive>
      <altPositive>None</altPositive>
      <negative>None</negative>
      <altNegative>None</altNegative>
      <deadZone>0.2</deadZone>
      <gravity>0</gravity>
      <sensitivity>1</sensitivity>
      <snap>false</snap>
      <invert>true</invert>
      <type>AnalogAxis</type>
      <axis>1</axis>
      <joystick>3</joystick>
    </AxisConfiguration>
    <AxisConfiguration name="LookHorizontal">
      <description />
      <positive>None</positive>
      <altPositive>None</altPositive>
      <negative>None</negative>
      <altNegative>None</altNegative>
      <deadZone>0.2</deadZone>
      <gravity>0</gravity>
      <sensitivity>1</sensitivity>
      <snap>false</snap>
      <invert>false</invert>
      <type>AnalogAxis</type>
      <axis>3</axis>
      <joystick>3</joystick>
    </AxisConfiguration>
    <AxisConfiguration name="LookVertical">
      <description />
      <positive>None</positive>
      <altPositive>None</altPositive>
      <negative>None</negative>
      <altNegative>None</altNegative>
      <deadZone>0.2</deadZone>
      <gravity>0</gravity>
      <sensitivity>1</sensitivity>
      <snap>false</snap>
      <invert>true</invert>
      <type>AnalogAxis</type>
      <axis>4</axis>
      <joystick>3</joystick>
    </AxisConfiguration>
    <AxisConfiguration name="Jump">
      <description />
      <positive>None</positive>
      <altPositive>None</altPositive>
      <negative>None</negative>
      <altNegative>None</altNegative>
      <deadZone>0</deadZone>
      <gravity>0</gravity>
      <sensitivity>1000</sensitivity>
      <snap>true</snap>
      <invert>false</invert>
      <type>AnalogAxis</type>
      <axis>8</axis>
      <joystick>3</joystick>
    </AxisConfiguration>
    <AxisConfiguration name="Fire">
      <description />
      <positive>None</positive>
      <altPositive>None</altPositive>
      <negative>None</negative>
      <altNegative>None</altNegative>
      <deadZone>0</deadZone>
      <gravity>0</gravity>
      <sensitivity>1000</sensitivity>
      <snap>true</snap>
      <invert>false</invert>
      <type>AnalogAxis</type>
      <axis>9</axis>
      <joystick>3</joystick>
    </AxisConfiguration>
    <AxisConfiguration name="Reload">
      <description />
      <positive>Joystick4Button0</positive>
      <altPositive>None</altPositive>
      <negative>None</negative>
      <altNegative>None</altNegative>
      <deadZone>0</deadZone>
      <gravity>0</gravity>
      <sensitivity>0</sensitivity>
      <snap>false</snap>
      <invert>false</invert>
      <type>Button</type>
      <axis>0</axis>
      <joystick>3</joystick>
    </AxisConfiguration>
    <AxisConfiguration name="Menu">
      <description />
      <positive>Joystick4Button7</positive>
      <altPositive>None</altPositive>
      <negative>None</negative>
      <altNegative>None</altNegative>
      <deadZone>0</deadZone>
      <gravity>0</gravity>
      <sensitivity>0</sensitivity>
      <snap>false</snap>
      <invert>false</invert>
      <type>Button</type>
      <axis>0</axis>
      <joystick>3</joystick>
    </AxisConfiguration>
    <AxisConfiguration name="DPADHorizontal">
      <description />
      <positive>None</positive>
      <altPositive>None</altPositive>
      <negative>None</negative>
      <altNegative>None</altNegative>
      <deadZone>0</deadZone>
      <gravity>0</gravity>
      <sensitivity>1000</sensitivity>
      <snap>true</snap>
      <invert>false</invert>
      <type>AnalogAxis</type>
      <axis>5</axis>
      <joystick>3</joystick>
    </AxisConfiguration>
    <AxisConfiguration name="DPADVertical">
      <description />
      <positive>None</positive>
      <altPositive>None</altPositive>
      <negative>None</negative>
      <altNegative>None</altNegative>
      <deadZone>0</deadZone>
      <gravity>0</gravity>
      <sensitivity>1000</sensitivity>
      <snap>true</snap>
      <invert>false</invert>
      <type>AnalogAxis</type>
      <axis>6</axis>
      <joystick>3</joystick>
    </AxisConfiguration>
    <AxisConfiguration name="RightBumper">
      <description />
      <positive>Joystick4Button5</positive>
      <altPositive>None</altPositive>
      <negative>None</negative>
      <altNegative>None</altNegative>
      <deadZone>0</deadZone>
      <gravity>0</gravity>
      <sensitivity>0</sensitivity>
      <snap>false</snap>
      <invert>false</invert>
      <type>Button</type>
      <axis>0</axis>
      <joystick>3</joystick>
    </AxisConfiguration>
    <AxisConfiguration name="LeftBumper">
      <description />
      <positive>Joystick4Button4</positive>
      <altPositive>None</altPositive>
      <negative>None</negative>
      <altNegative>None</altNegative>
      <deadZone>0</deadZone>
      <gravity>0</gravity>
      <sensitivity>0</sensitivity>
      <snap>false</snap>
      <invert>false</invert>
      <type>Button</type>
      <axis>0</axis>
      <joystick>3</joystick>
    </AxisConfiguration>
  </InputConfiguration>
  <InputConfiguration name="OSX_Gamepad1">
    <AxisConfiguration name="Horizontal">
      <description />
      <positive>None</positive>
      <altPositive>None</altPositive>
      <negative>None</negative>
      <altNegative>None</altNegative>
      <deadZone>0.2</deadZone>
      <gravity>0</gravity>
      <sensitivity>1</sensitivity>
      <snap>false</snap>
      <invert>false</invert>
      <type>AnalogAxis</type>
      <axis>0</axis>
      <joystick>0</joystick>
    </AxisConfiguration>
    <AxisConfiguration name="Vertical">
      <description />
      <positive>None</positive>
      <altPositive>None</altPositive>
      <negative>None</negative>
      <altNegative>None</altNegative>
      <deadZone>0.2</deadZone>
      <gravity>0</gravity>
      <sensitivity>1</sensitivity>
      <snap>false</snap>
      <invert>true</invert>
      <type>AnalogAxis</type>
      <axis>1</axis>
      <joystick>0</joystick>
    </AxisConfiguration>
    <AxisConfiguration name="LookHorizontal">
      <description />
      <positive>None</positive>
      <altPositive>None</altPositive>
      <negative>None</negative>
      <altNegative>None</altNegative>
      <deadZone>0.2</deadZone>
      <gravity>0</gravity>
      <sensitivity>1</sensitivity>
      <snap>false</snap>
      <invert>false</invert>
      <type>AnalogAxis</type>
      <axis>2</axis>
      <joystick>0</joystick>
    </AxisConfiguration>
    <AxisConfiguration name="LookVertical">
      <description />
      <positive>None</positive>
      <altPositive>None</altPositive>
      <negative>None</negative>
      <altNegative>None</altNegative>
      <deadZone>0.2</deadZone>
      <gravity>0</gravity>
      <sensitivity>1</sensitivity>
      <snap>false</snap>
      <invert>true</invert>
      <type>AnalogAxis</type>
      <axis>3</axis>
      <joystick>0</joystick>
    </AxisConfiguration>
    <AxisConfiguration name="Jump">
      <description />
      <positive>None</positive>
      <altPositive>None</altPositive>
      <negative>None</negative>
      <altNegative>None</altNegative>
      <deadZone>0</deadZone>
      <gravity>0</gravity>
      <sensitivity>1000</sensitivity>
      <snap>true</snap>
      <invert>false</invert>
      <type>AnalogAxis</type>
      <axis>4</axis>
      <joystick>0</joystick>
    </AxisConfiguration>
    <AxisConfiguration name="Fire">
      <description />
      <positive>None</positive>
      <altPositive>None</altPositive>
      <negative>None</negative>
      <altNegative>None</altNegative>
      <deadZone>0</deadZone>
      <gravity>0</gravity>
      <sensitivity>1000</sensitivity>
      <snap>true</snap>
      <invert>false</invert>
      <type>AnalogAxis</type>
      <axis>5</axis>
      <joystick>0</joystick>
    </AxisConfiguration>
    <AxisConfiguration name="Reload">
      <description />
      <positive>Joystick1Button16</positive>
      <altPositive>None</altPositive>
      <negative>None</negative>
      <altNegative>None</altNegative>
      <deadZone>0</deadZone>
      <gravity>0</gravity>
      <sensitivity>0</sensitivity>
      <snap>false</snap>
      <invert>false</invert>
      <type>Button</type>
      <axis>0</axis>
      <joystick>0</joystick>
    </AxisConfiguration>
    <AxisConfiguration name="Menu">
      <description />
      <positive>Joystick1Button9</positive>
      <altPositive>None</altPositive>
      <negative>None</negative>
      <altNegative>None</altNegative>
      <deadZone>0</deadZone>
      <gravity>0</gravity>
      <sensitivity>0</sensitivity>
      <snap>false</snap>
      <invert>false</invert>
      <type>Button</type>
      <axis>0</axis>
      <joystick>0</joystick>
    </AxisConfiguration>
    <AxisConfiguration name="DPADHorizontal">
      <description />
      <positive>None</positive>
      <altPositive>None</altPositive>
      <negative>None</negative>
      <altNegative>None</altNegative>
      <deadZone>0</deadZone>
      <gravity>0</gravity>
      <sensitivity>0</sensitivity>
      <snap>false</snap>
      <invert>false</invert>
      <type>Button</type>
      <axis>0</axis>
      <joystick>0</joystick>
    </AxisConfiguration>
    <AxisConfiguration name="DPADVertical">
      <description />
      <positive>None</positive>
      <altPositive>None</altPositive>
      <negative>None</negative>
      <altNegative>None</altNegative>
      <deadZone>0</deadZone>
      <gravity>0</gravity>
      <sensitivity>0</sensitivity>
      <snap>false</snap>
      <invert>false</invert>
      <type>Button</type>
      <axis>0</axis>
      <joystick>0</joystick>
    </AxisConfiguration>
    <AxisConfiguration name="RightBumper">
      <description />
      <positive>Joystick1Button14</positive>
      <altPositive>None</altPositive>
      <negative>None</negative>
      <altNegative>None</altNegative>
      <deadZone>0</deadZone>
      <gravity>0</gravity>
      <sensitivity>0</sensitivity>
      <snap>false</snap>
      <invert>false</invert>
      <type>Button</type>
      <axis>0</axis>
      <joystick>0</joystick>
    </AxisConfiguration>
    <AxisConfiguration name="LeftBumper">
      <description />
      <positive>Joystick1Button13</positive>
      <altPositive>None</altPositive>
      <negative>None</negative>
      <altNegative>None</altNegative>
      <deadZone>0</deadZone>
      <gravity>0</gravity>
      <sensitivity>0</sensitivity>
      <snap>false</snap>
      <invert>false</invert>
      <type>Button</type>
      <axis>0</axis>
      <joystick>0</joystick>
    </AxisConfiguration>
  </InputConfiguration>
  <InputConfiguration name="OSX_Gamepad2">
    <AxisConfiguration name="Horizontal">
      <description />
      <positive>None</positive>
      <altPositive>None</altPositive>
      <negative>None</negative>
      <altNegative>None</altNegative>
      <deadZone>0.2</deadZone>
      <gravity>0</gravity>
      <sensitivity>1</sensitivity>
      <snap>false</snap>
      <invert>false</invert>
      <type>AnalogAxis</type>
      <axis>0</axis>
      <joystick>1</joystick>
    </AxisConfiguration>
    <AxisConfiguration name="Vertical">
      <description />
      <positive>None</positive>
      <altPositive>None</altPositive>
      <negative>None</negative>
      <altNegative>None</altNegative>
      <deadZone>0.2</deadZone>
      <gravity>0</gravity>
      <sensitivity>1</sensitivity>
      <snap>false</snap>
      <invert>true</invert>
      <type>AnalogAxis</type>
      <axis>1</axis>
      <joystick>1</joystick>
    </AxisConfiguration>
    <AxisConfiguration name="LookHorizontal">
      <description />
      <positive>None</positive>
      <altPositive>None</altPositive>
      <negative>None</negative>
      <altNegative>None</altNegative>
      <deadZone>0.2</deadZone>
      <gravity>0</gravity>
      <sensitivity>1</sensitivity>
      <snap>false</snap>
      <invert>false</invert>
      <type>AnalogAxis</type>
      <axis>2</axis>
      <joystick>1</joystick>
    </AxisConfiguration>
    <AxisConfiguration name="LookVertical">
      <description />
      <positive>None</positive>
      <altPositive>None</altPositive>
      <negative>None</negative>
      <altNegative>None</altNegative>
      <deadZone>0.2</deadZone>
      <gravity>0</gravity>
      <sensitivity>1</sensitivity>
      <snap>false</snap>
      <invert>true</invert>
      <type>AnalogAxis</type>
      <axis>3</axis>
      <joystick>1</joystick>
    </AxisConfiguration>
    <AxisConfiguration name="Jump">
      <description />
      <positive>None</positive>
      <altPositive>None</altPositive>
      <negative>None</negative>
      <altNegative>None</altNegative>
      <deadZone>0</deadZone>
      <gravity>0</gravity>
      <sensitivity>1000</sensitivity>
      <snap>true</snap>
      <invert>false</invert>
      <type>AnalogAxis</type>
      <axis>4</axis>
      <joystick>1</joystick>
    </AxisConfiguration>
    <AxisConfiguration name="Fire">
      <description />
      <positive>None</positive>
      <altPositive>None</altPositive>
      <negative>None</negative>
      <altNegative>None</altNegative>
      <deadZone>0</deadZone>
      <gravity>0</gravity>
      <sensitivity>1000</sensitivity>
      <snap>true</snap>
      <invert>false</invert>
      <type>AnalogAxis</type>
      <axis>5</axis>
      <joystick>1</joystick>
    </AxisConfiguration>
    <AxisConfiguration name="Reload">
      <description />
      <positive>Joystick2Button16</positive>
      <altPositive>None</altPositive>
      <negative>None</negative>
      <altNegative>None</altNegative>
      <deadZone>0</deadZone>
      <gravity>0</gravity>
      <sensitivity>0</sensitivity>
      <snap>false</snap>
      <invert>false</invert>
      <type>Button</type>
      <axis>0</axis>
      <joystick>1</joystick>
    </AxisConfiguration>
    <AxisConfiguration name="Menu">
      <description />
      <positive>Joystick2Button9</positive>
      <altPositive>None</altPositive>
      <negative>None</negative>
      <altNegative>None</altNegative>
      <deadZone>0</deadZone>
      <gravity>0</gravity>
      <sensitivity>0</sensitivity>
      <snap>false</snap>
      <invert>false</invert>
      <type>Button</type>
      <axis>0</axis>
      <joystick>1</joystick>
    </AxisConfiguration>
    <AxisConfiguration name="DPADHorizontal">
      <description />
      <positive>None</positive>
      <altPositive>None</altPositive>
      <negative>None</negative>
      <altNegative>None</altNegative>
      <deadZone>0</deadZone>
      <gravity>0</gravity>
      <sensitivity>0</sensitivity>
      <snap>false</snap>
      <invert>false</invert>
      <type>Button</type>
      <axis>0</axis>
      <joystick>1</joystick>
    </AxisConfiguration>
    <AxisConfiguration name="DPADVertical">
      <description />
      <positive>None</positive>
      <altPositive>None</altPositive>
      <negative>None</negative>
      <altNegative>None</altNegative>
      <deadZone>0</deadZone>
      <gravity>0</gravity>
      <sensitivity>0</sensitivity>
      <snap>false</snap>
      <invert>false</invert>
      <type>Button</type>
      <axis>0</axis>
      <joystick>1</joystick>
    </AxisConfiguration>
    <AxisConfiguration name="RightBumper">
      <description />
      <positive>Joystick2Button14</positive>
      <altPositive>None</altPositive>
      <negative>None</negative>
      <altNegative>None</altNegative>
      <deadZone>0</deadZone>
      <gravity>0</gravity>
      <sensitivity>0</sensitivity>
      <snap>false</snap>
      <invert>false</invert>
      <type>Button</type>
      <axis>0</axis>
      <joystick>1</joystick>
    </AxisConfiguration>
    <AxisConfiguration name="LeftBumper">
      <description />
      <positive>Joystick2Button13</positive>
      <altPositive>None</altPositive>
      <negative>None</negative>
      <altNegative>None</altNegative>
      <deadZone>0</deadZone>
      <gravity>0</gravity>
      <sensitivity>0</sensitivity>
      <snap>false</snap>
      <invert>false</invert>
      <type>Button</type>
      <axis>0</axis>
      <joystick>1</joystick>
    </AxisConfiguration>
  </InputConfiguration>
  <InputConfiguration name="OSX_Gamepad3">
    <AxisConfiguration name="Horizontal">
      <description />
      <positive>None</positive>
      <altPositive>None</altPositive>
      <negative>None</negative>
      <altNegative>None</altNegative>
      <deadZone>0.2</deadZone>
      <gravity>0</gravity>
      <sensitivity>1</sensitivity>
      <snap>false</snap>
      <invert>false</invert>
      <type>AnalogAxis</type>
      <axis>0</axis>
      <joystick>2</joystick>
    </AxisConfiguration>
    <AxisConfiguration name="Vertical">
      <description />
      <positive>None</positive>
      <altPositive>None</altPositive>
      <negative>None</negative>
      <altNegative>None</altNegative>
      <deadZone>0.2</deadZone>
      <gravity>0</gravity>
      <sensitivity>1</sensitivity>
      <snap>false</snap>
      <invert>true</invert>
      <type>AnalogAxis</type>
      <axis>1</axis>
      <joystick>2</joystick>
    </AxisConfiguration>
    <AxisConfiguration name="LookHorizontal">
      <description />
      <positive>None</positive>
      <altPositive>None</altPositive>
      <negative>None</negative>
      <altNegative>None</altNegative>
      <deadZone>0.2</deadZone>
      <gravity>0</gravity>
      <sensitivity>1</sensitivity>
      <snap>false</snap>
      <invert>false</invert>
      <type>AnalogAxis</type>
      <axis>2</axis>
      <joystick>2</joystick>
    </AxisConfiguration>
    <AxisConfiguration name="LookVertical">
      <description />
      <positive>None</positive>
      <altPositive>None</altPositive>
      <negative>None</negative>
      <altNegative>None</altNegative>
      <deadZone>0.2</deadZone>
      <gravity>0</gravity>
      <sensitivity>1</sensitivity>
      <snap>false</snap>
      <invert>true</invert>
      <type>AnalogAxis</type>
      <axis>3</axis>
      <joystick>2</joystick>
    </AxisConfiguration>
    <AxisConfiguration name="Jump">
      <description />
      <positive>None</positive>
      <altPositive>None</altPositive>
      <negative>None</negative>
      <altNegative>None</altNegative>
      <deadZone>0</deadZone>
      <gravity>0</gravity>
      <sensitivity>1000</sensitivity>
      <snap>true</snap>
      <invert>false</invert>
      <type>AnalogAxis</type>
      <axis>4</axis>
      <joystick>2</joystick>
    </AxisConfiguration>
    <AxisConfiguration name="Fire">
      <description />
      <positive>None</positive>
      <altPositive>None</altPositive>
      <negative>None</negative>
      <altNegative>None</altNegative>
      <deadZone>0</deadZone>
      <gravity>0</gravity>
      <sensitivity>1000</sensitivity>
      <snap>true</snap>
      <invert>false</invert>
      <type>AnalogAxis</type>
      <axis>5</axis>
      <joystick>2</joystick>
    </AxisConfiguration>
    <AxisConfiguration name="Reload">
      <description />
      <positive>Joystick3Button16</positive>
      <altPositive>None</altPositive>
      <negative>None</negative>
      <altNegative>None</altNegative>
      <deadZone>0</deadZone>
      <gravity>0</gravity>
      <sensitivity>0</sensitivity>
      <snap>false</snap>
      <invert>false</invert>
      <type>Button</type>
      <axis>0</axis>
      <joystick>2</joystick>
    </AxisConfiguration>
    <AxisConfiguration name="Menu">
      <description />
      <positive>Joystick3Button9</positive>
      <altPositive>None</altPositive>
      <negative>None</negative>
      <altNegative>None</altNegative>
      <deadZone>0</deadZone>
      <gravity>0</gravity>
      <sensitivity>0</sensitivity>
      <snap>false</snap>
      <invert>false</invert>
      <type>Button</type>
      <axis>0</axis>
      <joystick>2</joystick>
    </AxisConfiguration>
    <AxisConfiguration name="DPADHorizontal">
      <description />
      <positive>None</positive>
      <altPositive>None</altPositive>
      <negative>None</negative>
      <altNegative>None</altNegative>
      <deadZone>0</deadZone>
      <gravity>0</gravity>
      <sensitivity>0</sensitivity>
      <snap>false</snap>
      <invert>false</invert>
      <type>Button</type>
      <axis>0</axis>
      <joystick>2</joystick>
    </AxisConfiguration>
    <AxisConfiguration name="DPADVertical">
      <description />
      <positive>None</positive>
      <altPositive>None</altPositive>
      <negative>None</negative>
      <altNegative>None</altNegative>
      <deadZone>0</deadZone>
      <gravity>0</gravity>
      <sensitivity>0</sensitivity>
      <snap>false</snap>
      <invert>false</invert>
      <type>Button</type>
      <axis>0</axis>
      <joystick>2</joystick>
    </AxisConfiguration>
    <AxisConfiguration name="RightBumper">
      <description />
      <positive>Joystick3Button14</positive>
      <altPositive>None</altPositive>
      <negative>None</negative>
      <altNegative>None</altNegative>
      <deadZone>0</deadZone>
      <gravity>0</gravity>
      <sensitivity>0</sensitivity>
      <snap>false</snap>
      <invert>false</invert>
      <type>Button</type>
      <axis>0</axis>
      <joystick>2</joystick>
    </AxisConfiguration>
    <AxisConfiguration name="LeftBumper">
      <description />
      <positive>Joystick3Button13</positive>
      <altPositive>None</altPositive>
      <negative>None</negative>
      <altNegative>None</altNegative>
      <deadZone>0</deadZone>
      <gravity>0</gravity>
      <sensitivity>0</sensitivity>
      <snap>false</snap>
      <invert>false</invert>
      <type>Button</type>
      <axis>0</axis>
      <joystick>2</joystick>
    </AxisConfiguration>
  </InputConfiguration>
  <InputConfiguration name="OSX_Gamepad4">
    <AxisConfiguration name="Horizontal">
      <description />
      <positive>None</positive>
      <altPositive>None</altPositive>
      <negative>None</negative>
      <altNegative>None</altNegative>
      <deadZone>0.2</deadZone>
      <gravity>0</gravity>
      <sensitivity>1</sensitivity>
      <snap>false</snap>
      <invert>false</invert>
      <type>AnalogAxis</type>
      <axis>0</axis>
      <joystick>3</joystick>
    </AxisConfiguration>
    <AxisConfiguration name="Vertical">
      <description />
      <positive>None</positive>
      <altPositive>None</altPositive>
      <negative>None</negative>
      <altNegative>None</altNegative>
      <deadZone>0.2</deadZone>
      <gravity>0</gravity>
      <sensitivity>1</sensitivity>
      <snap>false</snap>
      <invert>true</invert>
      <type>AnalogAxis</type>
      <axis>1</axis>
      <joystick>3</joystick>
    </AxisConfiguration>
    <AxisConfiguration name="LookHorizontal">
      <description />
      <positive>None</positive>
      <altPositive>None</altPositive>
      <negative>None</negative>
      <altNegative>None</altNegative>
      <deadZone>0.2</deadZone>
      <gravity>0</gravity>
      <sensitivity>1</sensitivity>
      <snap>false</snap>
      <invert>false</invert>
      <type>AnalogAxis</type>
      <axis>2</axis>
      <joystick>3</joystick>
    </AxisConfiguration>
    <AxisConfiguration name="LookVertical">
      <description />
      <positive>None</positive>
      <altPositive>None</altPositive>
      <negative>None</negative>
      <altNegative>None</altNegative>
      <deadZone>0.2</deadZone>
      <gravity>0</gravity>
      <sensitivity>1</sensitivity>
      <snap>false</snap>
      <invert>true</invert>
      <type>AnalogAxis</type>
      <axis>3</axis>
      <joystick>3</joystick>
    </AxisConfiguration>
    <AxisConfiguration name="Jump">
      <description />
      <positive>None</positive>
      <altPositive>None</altPositive>
      <negative>None</negative>
      <altNegative>None</altNegative>
      <deadZone>0</deadZone>
      <gravity>0</gravity>
      <sensitivity>1000</sensitivity>
      <snap>true</snap>
      <invert>false</invert>
      <type>AnalogAxis</type>
      <axis>4</axis>
      <joystick>3</joystick>
    </AxisConfiguration>
    <AxisConfiguration name="Fire">
      <description />
      <positive>None</positive>
      <altPositive>None</altPositive>
      <negative>None</negative>
      <altNegative>None</altNegative>
      <deadZone>0</deadZone>
      <gravity>0</gravity>
      <sensitivity>1000</sensitivity>
      <snap>true</snap>
      <invert>false</invert>
      <type>AnalogAxis</type>
      <axis>5</axis>
      <joystick>3</joystick>
    </AxisConfiguration>
    <AxisConfiguration name="Reload">
      <description />
      <positive>Joystick4Button16</positive>
      <altPositive>None</altPositive>
      <negative>None</negative>
      <altNegative>None</altNegative>
      <deadZone>0</deadZone>
      <gravity>0</gravity>
      <sensitivity>0</sensitivity>
      <snap>false</snap>
      <invert>false</invert>
      <type>Button</type>
      <axis>0</axis>
      <joystick>3</joystick>
    </AxisConfiguration>
    <AxisConfiguration name="Menu">
      <description />
      <positive>Joystick4Button9</positive>
      <altPositive>None</altPositive>
      <negative>None</negative>
      <altNegative>None</altNegative>
      <deadZone>0</deadZone>
      <gravity>0</gravity>
      <sensitivity>0</sensitivity>
      <snap>false</snap>
      <invert>false</invert>
      <type>Button</type>
      <axis>0</axis>
      <joystick>3</joystick>
    </AxisConfiguration>
    <AxisConfiguration name="DPADHorizontal">
      <description />
      <positive>None</positive>
      <altPositive>None</altPositive>
      <negative>None</negative>
      <altNegative>None</altNegative>
      <deadZone>0</deadZone>
      <gravity>0</gravity>
      <sensitivity>0</sensitivity>
      <snap>false</snap>
      <invert>false</invert>
      <type>Button</type>
      <axis>0</axis>
      <joystick>3</joystick>
    </AxisConfiguration>
    <AxisConfiguration name="DPADVertical">
      <description />
      <positive>None</positive>
      <altPositive>None</altPositive>
      <negative>None</negative>
      <altNegative>None</altNegative>
      <deadZone>0</deadZone>
      <gravity>0</gravity>
      <sensitivity>0</sensitivity>
      <snap>false</snap>
      <invert>false</invert>
      <type>Button</type>
      <axis>0</axis>
      <joystick>3</joystick>
    </AxisConfiguration>
    <AxisConfiguration name="RightBumper">
      <description />
      <positive>Joystick4Button14</positive>
      <altPositive>None</altPositive>
      <negative>None</negative>
      <altNegative>None</altNegative>
      <deadZone>0</deadZone>
      <gravity>0</gravity>
      <sensitivity>0</sensitivity>
      <snap>false</snap>
      <invert>false</invert>
      <type>Button</type>
      <axis>0</axis>
      <joystick>3</joystick>
    </AxisConfiguration>
    <AxisConfiguration name="LeftBumper">
      <description />
      <positive>Joystick4Button13</positive>
      <altPositive>None</altPositive>
      <negative>None</negative>
      <altNegative>None</altNegative>
      <deadZone>0</deadZone>
      <gravity>0</gravity>
      <sensitivity>0</sensitivity>
      <snap>false</snap>
      <invert>false</invert>
      <type>Button</type>
      <axis>0</axis>
      <joystick>3</joystick>
    </AxisConfiguration>
  </InputConfiguration>
  <InputConfiguration name="Linux_Gamepad1">
    <AxisConfiguration name="Horizontal">
      <description />
      <positive>None</positive>
      <altPositive>None</altPositive>
      <negative>None</negative>
      <altNegative>None</altNegative>
      <deadZone>0.2</deadZone>
      <gravity>0</gravity>
      <sensitivity>1</sensitivity>
      <snap>false</snap>
      <invert>false</invert>
      <type>AnalogAxis</type>
      <axis>0</axis>
      <joystick>0</joystick>
    </AxisConfiguration>
    <AxisConfiguration name="Vertical">
      <description />
      <positive>None</positive>
      <altPositive>None</altPositive>
      <negative>None</negative>
      <altNegative>None</altNegative>
      <deadZone>0.2</deadZone>
      <gravity>0</gravity>
      <sensitivity>1</sensitivity>
      <snap>false</snap>
      <invert>true</invert>
      <type>AnalogAxis</type>
      <axis>1</axis>
      <joystick>0</joystick>
    </AxisConfiguration>
    <AxisConfiguration name="LookHorizontal">
      <description />
      <positive>None</positive>
      <altPositive>None</altPositive>
      <negative>None</negative>
      <altNegative>None</altNegative>
      <deadZone>0.2</deadZone>
      <gravity>0</gravity>
      <sensitivity>1</sensitivity>
      <snap>false</snap>
      <invert>false</invert>
      <type>AnalogAxis</type>
      <axis>3</axis>
      <joystick>0</joystick>
    </AxisConfiguration>
    <AxisConfiguration name="LookVertical">
      <description />
      <positive>None</positive>
      <altPositive>None</altPositive>
      <negative>None</negative>
      <altNegative>None</altNegative>
      <deadZone>0.2</deadZone>
      <gravity>0</gravity>
      <sensitivity>1</sensitivity>
      <snap>false</snap>
      <invert>true</invert>
      <type>AnalogAxis</type>
      <axis>4</axis>
      <joystick>0</joystick>
    </AxisConfiguration>
    <AxisConfiguration name="Jump">
      <description />
      <positive>None</positive>
      <altPositive>None</altPositive>
      <negative>None</negative>
      <altNegative>None</altNegative>
      <deadZone>0</deadZone>
      <gravity>0</gravity>
      <sensitivity>1000</sensitivity>
      <snap>true</snap>
      <invert>false</invert>
      <type>AnalogAxis</type>
      <axis>2</axis>
      <joystick>0</joystick>
    </AxisConfiguration>
    <AxisConfiguration name="Fire">
      <description />
      <positive>None</positive>
      <altPositive>None</altPositive>
      <negative>None</negative>
      <altNegative>None</altNegative>
      <deadZone>0</deadZone>
      <gravity>0</gravity>
      <sensitivity>1000</sensitivity>
      <snap>true</snap>
      <invert>false</invert>
      <type>AnalogAxis</type>
      <axis>5</axis>
      <joystick>0</joystick>
    </AxisConfiguration>
    <AxisConfiguration name="Reload">
      <description />
      <positive>Joystick1Button0</positive>
      <altPositive>None</altPositive>
      <negative>None</negative>
      <altNegative>None</altNegative>
      <deadZone>0</deadZone>
      <gravity>0</gravity>
      <sensitivity>0</sensitivity>
      <snap>false</snap>
      <invert>false</invert>
      <type>Button</type>
      <axis>0</axis>
      <joystick>0</joystick>
    </AxisConfiguration>
    <AxisConfiguration name="Menu">
      <description />
      <positive>Joystick1Button7</positive>
      <altPositive>None</altPositive>
      <negative>None</negative>
      <altNegative>None</altNegative>
      <deadZone>0</deadZone>
      <gravity>0</gravity>
      <sensitivity>0</sensitivity>
      <snap>false</snap>
      <invert>false</invert>
      <type>Button</type>
      <axis>0</axis>
      <joystick>0</joystick>
    </AxisConfiguration>
    <AxisConfiguration name="DPADHorizontal">
      <description />
      <positive>None</positive>
      <altPositive>None</altPositive>
      <negative>None</negative>
      <altNegative>None</altNegative>
      <deadZone>0</deadZone>
      <gravity>0</gravity>
      <sensitivity>1000</sensitivity>
      <snap>true</snap>
      <invert>false</invert>
      <type>AnalogAxis</type>
      <axis>6</axis>
      <joystick>0</joystick>
    </AxisConfiguration>
    <AxisConfiguration name="DPADVertical">
      <description />
      <positive>None</positive>
      <altPositive>None</altPositive>
      <negative>None</negative>
      <altNegative>None</altNegative>
      <deadZone>0</deadZone>
      <gravity>0</gravity>
      <sensitivity>1000</sensitivity>
      <snap>true</snap>
      <invert>false</invert>
      <type>AnalogAxis</type>
      <axis>7</axis>
      <joystick>0</joystick>
    </AxisConfiguration>
    <AxisConfiguration name="RightBumper">
      <description />
      <positive>Joystick1Button5</positive>
      <altPositive>None</altPositive>
      <negative>None</negative>
      <altNegative>None</altNegative>
      <deadZone>0</deadZone>
      <gravity>0</gravity>
      <sensitivity>0</sensitivity>
      <snap>false</snap>
      <invert>false</invert>
      <type>Button</type>
      <axis>0</axis>
      <joystick>0</joystick>
    </AxisConfiguration>
    <AxisConfiguration name="LeftBumper">
      <description />
      <positive>Joystick1Button4</positive>
      <altPositive>None</altPositive>
      <negative>None</negative>
      <altNegative>None</altNegative>
      <deadZone>0</deadZone>
      <gravity>0</gravity>
      <sensitivity>0</sensitivity>
      <snap>false</snap>
      <invert>false</invert>
      <type>Button</type>
      <axis>0</axis>
      <joystick>0</joystick>
    </AxisConfiguration>
  </InputConfiguration>
  <InputConfiguration name="Linux_Gamepad2">
    <AxisConfiguration name="Horizontal">
      <description />
      <positive>None</positive>
      <altPositive>None</altPositive>
      <negative>None</negative>
      <altNegative>None</altNegative>
      <deadZone>0.2</deadZone>
      <gravity>0</gravity>
      <sensitivity>1</sensitivity>
      <snap>false</snap>
      <invert>false</invert>
      <type>AnalogAxis</type>
      <axis>0</axis>
      <joystick>1</joystick>
    </AxisConfiguration>
    <AxisConfiguration name="Vertical">
      <description />
      <positive>None</positive>
      <altPositive>None</altPositive>
      <negative>None</negative>
      <altNegative>None</altNegative>
      <deadZone>0.2</deadZone>
      <gravity>0</gravity>
      <sensitivity>1</sensitivity>
      <snap>false</snap>
      <invert>true</invert>
      <type>AnalogAxis</type>
      <axis>1</axis>
      <joystick>1</joystick>
    </AxisConfiguration>
    <AxisConfiguration name="LookHorizontal">
      <description />
      <positive>None</positive>
      <altPositive>None</altPositive>
      <negative>None</negative>
      <altNegative>None</altNegative>
      <deadZone>0.2</deadZone>
      <gravity>0</gravity>
      <sensitivity>1</sensitivity>
      <snap>false</snap>
      <invert>false</invert>
      <type>AnalogAxis</type>
      <axis>3</axis>
      <joystick>1</joystick>
    </AxisConfiguration>
    <AxisConfiguration name="LookVertical">
      <description />
      <positive>None</positive>
      <altPositive>None</altPositive>
      <negative>None</negative>
      <altNegative>None</altNegative>
      <deadZone>0.2</deadZone>
      <gravity>0</gravity>
      <sensitivity>1</sensitivity>
      <snap>false</snap>
      <invert>true</invert>
      <type>AnalogAxis</type>
      <axis>4</axis>
      <joystick>1</joystick>
    </AxisConfiguration>
    <AxisConfiguration name="Jump">
      <description />
      <positive>None</positive>
      <altPositive>None</altPositive>
      <negative>None</negative>
      <altNegative>None</altNegative>
      <deadZone>0</deadZone>
      <gravity>0</gravity>
      <sensitivity>1000</sensitivity>
      <snap>true</snap>
      <invert>false</invert>
      <type>AnalogAxis</type>
      <axis>2</axis>
      <joystick>1</joystick>
    </AxisConfiguration>
    <AxisConfiguration name="Fire">
      <description />
      <positive>None</positive>
      <altPositive>None</altPositive>
      <negative>None</negative>
      <altNegative>None</altNegative>
      <deadZone>0</deadZone>
      <gravity>0</gravity>
      <sensitivity>1000</sensitivity>
      <snap>true</snap>
      <invert>false</invert>
      <type>AnalogAxis</type>
      <axis>5</axis>
      <joystick>1</joystick>
    </AxisConfiguration>
    <AxisConfiguration name="Reload">
      <description />
      <positive>Joystick2Button0</positive>
      <altPositive>None</altPositive>
      <negative>None</negative>
      <altNegative>None</altNegative>
      <deadZone>0</deadZone>
      <gravity>0</gravity>
      <sensitivity>0</sensitivity>
      <snap>false</snap>
      <invert>false</invert>
      <type>Button</type>
      <axis>0</axis>
      <joystick>1</joystick>
    </AxisConfiguration>
    <AxisConfiguration name="Menu">
      <description />
      <positive>Joystick2Button7</positive>
      <altPositive>None</altPositive>
      <negative>None</negative>
      <altNegative>None</altNegative>
      <deadZone>0</deadZone>
      <gravity>0</gravity>
      <sensitivity>0</sensitivity>
      <snap>false</snap>
      <invert>false</invert>
      <type>Button</type>
      <axis>0</axis>
      <joystick>1</joystick>
    </AxisConfiguration>
    <AxisConfiguration name="DPADHorizontal">
      <description />
      <positive>None</positive>
      <altPositive>None</altPositive>
      <negative>None</negative>
      <altNegative>None</altNegative>
      <deadZone>0</deadZone>
      <gravity>0</gravity>
      <sensitivity>1000</sensitivity>
      <snap>true</snap>
      <invert>false</invert>
      <type>AnalogAxis</type>
      <axis>6</axis>
      <joystick>1</joystick>
    </AxisConfiguration>
    <AxisConfiguration name="DPADVertical">
      <description />
      <positive>None</positive>
      <altPositive>None</altPositive>
      <negative>None</negative>
      <altNegative>None</altNegative>
      <deadZone>0</deadZone>
      <gravity>0</gravity>
      <sensitivity>1000</sensitivity>
      <snap>true</snap>
      <invert>false</invert>
      <type>AnalogAxis</type>
      <axis>7</axis>
      <joystick>1</joystick>
    </AxisConfiguration>
    <AxisConfiguration name="RightBumper">
      <description />
      <positive>Joystick2Button5</positive>
      <altPositive>None</altPositive>
      <negative>None</negative>
      <altNegative>None</altNegative>
      <deadZone>0</deadZone>
      <gravity>0</gravity>
      <sensitivity>0</sensitivity>
      <snap>false</snap>
      <invert>false</invert>
      <type>Button</type>
      <axis>0</axis>
      <joystick>1</joystick>
    </AxisConfiguration>
    <AxisConfiguration name="LeftBumper">
      <description />
      <positive>Joystick2Button4</positive>
      <altPositive>None</altPositive>
      <negative>None</negative>
      <altNegative>None</altNegative>
      <deadZone>0</deadZone>
      <gravity>0</gravity>
      <sensitivity>0</sensitivity>
      <snap>false</snap>
      <invert>false</invert>
      <type>Button</type>
      <axis>0</axis>
      <joystick>1</joystick>
    </AxisConfiguration>
  </InputConfiguration>
  <InputConfiguration name="Linux_Gamepad3">
    <AxisConfiguration name="Horizontal">
      <description />
      <positive>None</positive>
      <altPositive>None</altPositive>
      <negative>None</negative>
      <altNegative>None</altNegative>
      <deadZone>0.2</deadZone>
      <gravity>0</gravity>
      <sensitivity>1</sensitivity>
      <snap>false</snap>
      <invert>false</invert>
      <type>AnalogAxis</type>
      <axis>0</axis>
      <joystick>2</joystick>
    </AxisConfiguration>
    <AxisConfiguration name="Vertical">
      <description />
      <positive>None</positive>
      <altPositive>None</altPositive>
      <negative>None</negative>
      <altNegative>None</altNegative>
      <deadZone>0.2</deadZone>
      <gravity>0</gravity>
      <sensitivity>1</sensitivity>
      <snap>false</snap>
      <invert>true</invert>
      <type>AnalogAxis</type>
      <axis>1</axis>
      <joystick>2</joystick>
    </AxisConfiguration>
    <AxisConfiguration name="LookHorizontal">
      <description />
      <positive>None</positive>
      <altPositive>None</altPositive>
      <negative>None</negative>
      <altNegative>None</altNegative>
      <deadZone>0.2</deadZone>
      <gravity>0</gravity>
      <sensitivity>1</sensitivity>
      <snap>false</snap>
      <invert>false</invert>
      <type>AnalogAxis</type>
      <axis>3</axis>
      <joystick>2</joystick>
    </AxisConfiguration>
    <AxisConfiguration name="LookVertical">
      <description />
      <positive>None</positive>
      <altPositive>None</altPositive>
      <negative>None</negative>
      <altNegative>None</altNegative>
      <deadZone>0.2</deadZone>
      <gravity>0</gravity>
      <sensitivity>1</sensitivity>
      <snap>false</snap>
      <invert>true</invert>
      <type>AnalogAxis</type>
      <axis>4</axis>
      <joystick>2</joystick>
    </AxisConfiguration>
    <AxisConfiguration name="Jump">
      <description />
      <positive>None</positive>
      <altPositive>None</altPositive>
      <negative>None</negative>
      <altNegative>None</altNegative>
      <deadZone>0</deadZone>
      <gravity>0</gravity>
      <sensitivity>1000</sensitivity>
      <snap>true</snap>
      <invert>false</invert>
      <type>AnalogAxis</type>
      <axis>2</axis>
      <joystick>2</joystick>
    </AxisConfiguration>
    <AxisConfiguration name="Fire">
      <description />
      <positive>None</positive>
      <altPositive>None</altPositive>
      <negative>None</negative>
      <altNegative>None</altNegative>
      <deadZone>0</deadZone>
      <gravity>0</gravity>
      <sensitivity>1000</sensitivity>
      <snap>true</snap>
      <invert>false</invert>
      <type>AnalogAxis</type>
      <axis>5</axis>
      <joystick>2</joystick>
    </AxisConfiguration>
    <AxisConfiguration name="Reload">
      <description />
      <positive>Joystick3Button0</positive>
      <altPositive>None</altPositive>
      <negative>None</negative>
      <altNegative>None</altNegative>
      <deadZone>0</deadZone>
      <gravity>0</gravity>
      <sensitivity>0</sensitivity>
      <snap>false</snap>
      <invert>false</invert>
      <type>Button</type>
      <axis>0</axis>
      <joystick>2</joystick>
    </AxisConfiguration>
    <AxisConfiguration name="Menu">
      <description />
      <positive>Joystick3Button7</positive>
      <altPositive>None</altPositive>
      <negative>None</negative>
      <altNegative>None</altNegative>
      <deadZone>0</deadZone>
      <gravity>0</gravity>
      <sensitivity>0</sensitivity>
      <snap>false</snap>
      <invert>false</invert>
      <type>Button</type>
      <axis>0</axis>
      <joystick>2</joystick>
    </AxisConfiguration>
    <AxisConfiguration name="DPADHorizontal">
      <description />
      <positive>None</positive>
      <altPositive>None</altPositive>
      <negative>None</negative>
      <altNegative>None</altNegative>
      <deadZone>0</deadZone>
      <gravity>0</gravity>
      <sensitivity>1000</sensitivity>
      <snap>true</snap>
      <invert>false</invert>
      <type>AnalogAxis</type>
      <axis>6</axis>
      <joystick>2</joystick>
    </AxisConfiguration>
    <AxisConfiguration name="DPADVertical">
      <description />
      <positive>None</positive>
      <altPositive>None</altPositive>
      <negative>None</negative>
      <altNegative>None</altNegative>
      <deadZone>0</deadZone>
      <gravity>0</gravity>
      <sensitivity>1000</sensitivity>
      <snap>true</snap>
      <invert>false</invert>
      <type>AnalogAxis</type>
      <axis>7</axis>
      <joystick>2</joystick>
    </AxisConfiguration>
    <AxisConfiguration name="RightBumper">
      <description />
      <positive>Joystick3Button5</positive>
      <altPositive>None</altPositive>
      <negative>None</negative>
      <altNegative>None</altNegative>
      <deadZone>0</deadZone>
      <gravity>0</gravity>
      <sensitivity>0</sensitivity>
      <snap>false</snap>
      <invert>false</invert>
      <type>Button</type>
      <axis>0</axis>
      <joystick>2</joystick>
    </AxisConfiguration>
    <AxisConfiguration name="LeftBumper">
      <description />
      <positive>Joystick3Button4</positive>
      <altPositive>None</altPositive>
      <negative>None</negative>
      <altNegative>None</altNegative>
      <deadZone>0</deadZone>
      <gravity>0</gravity>
      <sensitivity>0</sensitivity>
      <snap>false</snap>
      <invert>false</invert>
      <type>Button</type>
      <axis>0</axis>
      <joystick>2</joystick>
    </AxisConfiguration>
  </InputConfiguration>
  <InputConfiguration name="Linux_Gamepad4">
    <AxisConfiguration name="Horizontal">
      <description />
      <positive>None</positive>
      <altPositive>None</altPositive>
      <negative>None</negative>
      <altNegative>None</altNegative>
      <deadZone>0.2</deadZone>
      <gravity>0</gravity>
      <sensitivity>1</sensitivity>
      <snap>false</snap>
      <invert>false</invert>
      <type>AnalogAxis</type>
      <axis>0</axis>
      <joystick>3</joystick>
    </AxisConfiguration>
    <AxisConfiguration name="Vertical">
      <description />
      <positive>None</positive>
      <altPositive>None</altPositive>
      <negative>None</negative>
      <altNegative>None</altNegative>
      <deadZone>0.2</deadZone>
      <gravity>0</gravity>
      <sensitivity>1</sensitivity>
      <snap>false</snap>
      <invert>true</invert>
      <type>AnalogAxis</type>
      <axis>1</axis>
      <joystick>3</joystick>
    </AxisConfiguration>
    <AxisConfiguration name="LookHorizontal">
      <description />
      <positive>None</positive>
      <altPositive>None</altPositive>
      <negative>None</negative>
      <altNegative>None</altNegative>
      <deadZone>0.2</deadZone>
      <gravity>0</gravity>
      <sensitivity>1</sensitivity>
      <snap>false</snap>
      <invert>false</invert>
      <type>AnalogAxis</type>
      <axis>3</axis>
      <joystick>3</joystick>
    </AxisConfiguration>
    <AxisConfiguration name="LookVertical">
      <description />
      <positive>None</positive>
      <altPositive>None</altPositive>
      <negative>None</negative>
      <altNegative>None</altNegative>
      <deadZone>0.2</deadZone>
      <gravity>0</gravity>
      <sensitivity>1</sensitivity>
      <snap>false</snap>
      <invert>true</invert>
      <type>AnalogAxis</type>
      <axis>4</axis>
      <joystick>3</joystick>
    </AxisConfiguration>
    <AxisConfiguration name="Jump">
      <description />
      <positive>None</positive>
      <altPositive>None</altPositive>
      <negative>None</negative>
      <altNegative>None</altNegative>
      <deadZone>0</deadZone>
      <gravity>0</gravity>
      <sensitivity>1000</sensitivity>
      <snap>true</snap>
      <invert>false</invert>
      <type>AnalogAxis</type>
      <axis>2</axis>
      <joystick>3</joystick>
    </AxisConfiguration>
    <AxisConfiguration name="Fire">
      <description />
      <positive>None</positive>
      <altPositive>None</altPositive>
      <negative>None</negative>
      <altNegative>None</altNegative>
      <deadZone>0</deadZone>
      <gravity>0</gravity>
      <sensitivity>1000</sensitivity>
      <snap>true</snap>
      <invert>false</invert>
      <type>AnalogAxis</type>
      <axis>5</axis>
      <joystick>3</joystick>
    </AxisConfiguration>
    <AxisConfiguration name="Reload">
      <description />
      <positive>Joystick4Button0</positive>
      <altPositive>None</altPositive>
      <negative>None</negative>
      <altNegative>None</altNegative>
      <deadZone>0</deadZone>
      <gravity>0</gravity>
      <sensitivity>0</sensitivity>
      <snap>false</snap>
      <invert>false</invert>
      <type>Button</type>
      <axis>0</axis>
      <joystick>3</joystick>
    </AxisConfiguration>
    <AxisConfiguration name="Menu">
      <description />
      <positive>Joystick4Button7</positive>
      <altPositive>None</altPositive>
      <negative>None</negative>
      <altNegative>None</altNegative>
      <deadZone>0</deadZone>
      <gravity>0</gravity>
      <sensitivity>0</sensitivity>
      <snap>false</snap>
      <invert>false</invert>
      <type>Button</type>
      <axis>0</axis>
      <joystick>3</joystick>
    </AxisConfiguration>
    <AxisConfiguration name="DPADHorizontal">
      <description />
      <positive>None</positive>
      <altPositive>None</altPositive>
      <negative>None</negative>
      <altNegative>None</altNegative>
      <deadZone>0</deadZone>
      <gravity>0</gravity>
      <sensitivity>1000</sensitivity>
      <snap>true</snap>
      <invert>false</invert>
      <type>AnalogAxis</type>
      <axis>6</axis>
      <joystick>3</joystick>
    </AxisConfiguration>
    <AxisConfiguration name="DPADVertical">
      <description />
      <positive>None</positive>
      <altPositive>None</altPositive>
      <negative>None</negative>
      <altNegative>None</altNegative>
      <deadZone>0</deadZone>
      <gravity>0</gravity>
      <sensitivity>1000</sensitivity>
      <snap>true</snap>
      <invert>false</invert>
      <type>AnalogAxis</type>
      <axis>7</axis>
      <joystick>3</joystick>
    </AxisConfiguration>
    <AxisConfiguration name="RightBumper">
      <description />
      <positive>Joystick4Button5</positive>
      <altPositive>None</altPositive>
      <negative>None</negative>
      <altNegative>None</altNegative>
      <deadZone>0</deadZone>
      <gravity>0</gravity>
      <sensitivity>0</sensitivity>
      <snap>false</snap>
      <invert>false</invert>
      <type>Button</type>
      <axis>0</axis>
      <joystick>3</joystick>
    </AxisConfiguration>
    <AxisConfiguration name="LeftBumper">
      <description />
      <positive>Joystick4Button4</positive>
      <altPositive>None</altPositive>
      <negative>None</negative>
      <altNegative>None</altNegative>
      <deadZone>0</deadZone>
      <gravity>0</gravity>
      <sensitivity>0</sensitivity>
      <snap>false</snap>
      <invert>false</invert>
      <type>Button</type>
      <axis>0</axis>
      <joystick>3</joystick>
    </AxisConfiguration>
  </InputConfiguration>
</Input>